youtube/__init__.py
youtube/youtube.py
youtube/exceptions/__init__.py
youtube/exceptions/exceptions.py
youtube/models/__init__.py
youtube/models/channel_model.py
youtube/models/comment_model.py
youtube/models/comment_thread_model.py
youtube/models/playlist_item_model.py
youtube/models/playlist_model.py
youtube/models/resource_saver_mixins.py
youtube/models/video_model.py
youtube/oauth/__init__.py
youtube/oauth/oauth.py
youtube/resources/__init__.py
youtube/resources/factories.py
youtube/resources/param_generator.py
youtube/resources/resource.py
youtube/resources/resource_id_parser.py
youtube/resources/response_parsers.py
youtube/resources/channel/__init__.py
youtube/resources/channel/channel_factories.py
youtube/resources/channel/channel_params_generator.py
youtube/resources/channel/channel_resource.py
youtube/resources/channel/find_parser.py
youtube/resources/channel/search_parser.py
youtube/resources/comment_thread/__init__.py
youtube/resources/comment_thread/comment_thread_factories.py
youtube/resources/comment_thread/comment_thread_resource.py
youtube/resources/comment_thread/params_generator.py
youtube/resources/comment_thread/response_parser.py
youtube/resources/mixins/__init__.py
youtube/resources/mixins/channel_mixin.py
youtube/resources/mixins/comment_mixin.py
youtube/resources/mixins/decorators.py
youtube/resources/mixins/playlist_mixin.py
youtube/resources/mixins/resource_list.py
youtube/resources/mixins/video_mixin.py
youtube/resources/playlist/__init__.py
youtube/resources/playlist/find_parser copy.py
youtube/resources/playlist/find_parser.py
youtube/resources/playlist/playlist_factory copy.py
youtube/resources/playlist/playlist_factory.py
youtube/resources/playlist/playlist_params_generator copy.py
youtube/resources/playlist/playlist_params_generator.py
youtube/resources/playlist/playlist_resource copy.py
youtube/resources/playlist/playlist_resource.py
youtube/resources/playlist/search_parser copy.py
youtube/resources/playlist/search_parser.py
ayv-0.5.1.dist-info/LICENSE
ayv-0.5.1.dist-info/METADATA
ayv-0.5.1.dist-info/WHEEL
ayv-0.5.1.dist-info/top_level.txt
ayv-0.5.1.dist-info/RECORD
